[
  {
    "name": "link",
    "defaultPalette": 0,
    "display": "Link",
    "separatePatches": false,
    "expand": 1
  },
  {
    "name": "marin",
    "defaultPalette": 3,
    "display": "Marin",
    "separatePatches": true,
    "expand": 1
  },
  {
    "name": "demonlink",
    "defaultPalette": 5,
    "display": "Demonic Link",
    "separatePatches": false,
    "expand": 1
  },
  {
    "name": "likelike",
    "defaultPalette": 3,
    "display": "Like-Like",
    "separatePatches": true,
    "expand": 1
  },
  {
    "name": "nayru",
    "defaultPalette": 3,
    "display": "Nayru",
    "separatePatches": true,
    "expand": 2
  }
]
